CHANGES.rst
CREDITS
LICENSE
MANIFEST.in
README.rst
setup.cfg
setup.py
tox.ini
doc/Makefile
doc/changes.rst
doc/conf.py
doc/configuration.rst
doc/customization.rst
doc/index.rst
doc/license.rst
doc/usage.rst
sphinxcontrib/__init__.py
sphinxcontrib/issuetracker/__init__.py
sphinxcontrib/issuetracker/issuetracker.css
sphinxcontrib/issuetracker/resolvers.py
sphinxcontrib_issuetracker.egg-info/PKG-INFO
sphinxcontrib_issuetracker.egg-info/SOURCES.txt
sphinxcontrib_issuetracker.egg-info/dependency_links.txt
sphinxcontrib_issuetracker.egg-info/namespace_packages.txt
sphinxcontrib_issuetracker.egg-info/not-zip-safe
sphinxcontrib_issuetracker.egg-info/requires.txt
sphinxcontrib_issuetracker.egg-info/top_level.txt
tests/conftest.py
tests/pypi.py
tests/test_builtin_trackers.py
tests/test_lookup.py
tests/test_pypi.py
tests/test_resolval.py
tests/test_role.py
tests/test_setup.py
tests/test_stylesheet.py
tests/test_tracker_config.py
tests/test_transformer.py