Metadata-Version: 1.1
Name: sphinxcontrib-issuetracker
Version: 0.10.1
Summary: Sphinx integration with different issuetrackers
Home-page: http://sphinxcontrib-issuetracker.readthedocs.org/
Author: Sebastian Wiesner
Author-email: lunaryorn@googlemail.com
License: BSD
Platform: any
Classifier: Development Status :: 4 - Beta
Classifier: Environment :: Console
Classifier: Environment :: Web Environment
Classifier: Intended Audience :: Developers
Classifier: License :: OSI Approved :: BSD License
Classifier: Operating System :: OS Independent
Classifier: Programming Language :: Python
Classifier: Programming Language :: Python :: 2
Classifier: Programming Language :: Python :: 3
Classifier: Topic :: Documentation
Classifier: Topic :: Utilities
